pyneuroml/__init__.py
pyneuroml/annotations.py
pyneuroml/biosimulations.py
pyneuroml/errors.py
pyneuroml/io.py
pyneuroml/modelgraphs.py
pyneuroml/nsgr.py
pyneuroml/pynml.py
pyneuroml/runners.py
pyneuroml/validators.py
pyneuroml/analysis/ChannelDensityPlot.py
pyneuroml/analysis/ChannelHelper.py
pyneuroml/analysis/ChannelInfo_TEMPLATE.html
pyneuroml/analysis/ChannelInfo_TEMPLATE.md
pyneuroml/analysis/LEMS_Test_TEMPLATE.xml
pyneuroml/analysis/NML2ChannelAnalysis.py
pyneuroml/analysis/__init__.py
pyneuroml/archive/__init__.py
pyneuroml/channelml/ChannelML2NeuroML2.xsl
pyneuroml/channelml/ChannelML2NeuroML2beta.xsl
pyneuroml/channelml/__init__.py
pyneuroml/lems/LEMSSimulation.py
pyneuroml/lems/LEMS_TEMPLATE.xml
pyneuroml/lems/__init__.py
pyneuroml/lib/jNeuroML-0.14.0-jar-with-dependencies.jar
pyneuroml/neuron/TEMPLATE.channel.nml
pyneuroml/neuron/__init__.py
pyneuroml/neuron/mview_neuroml1.hoc
pyneuroml/neuron/mview_neuroml2.hoc
pyneuroml/neuron/nrn_export_utils.py
pyneuroml/neuron/utils.hoc
pyneuroml/neuron/analysis/HHanalyse.py
pyneuroml/neuron/analysis/__init__.py
pyneuroml/plot/Plot.py
pyneuroml/plot/PlotMorphology.py
pyneuroml/plot/PlotMorphologyPlotly.py
pyneuroml/plot/PlotMorphologyVispy.py
pyneuroml/plot/PlotSpikes.py
pyneuroml/plot/PlotTimeSeries.py
pyneuroml/plot/__init__.py
pyneuroml/povray/MakeMovie.py
pyneuroml/povray/NeuroML2ToPOVRay.py
pyneuroml/povray/OverlaySimulation.py
pyneuroml/povray/__init__.py
pyneuroml/sbml/__init__.py
pyneuroml/sedml/__init__.py
pyneuroml/swc/ExportNML.py
pyneuroml/swc/ExportSWC.py
pyneuroml/swc/LoadSWC.py
pyneuroml/swc/__init__.py
pyneuroml/tellurium/__init__.py
pyneuroml/tune/NeuroMLController.py
pyneuroml/tune/NeuroMLSimulation.py
pyneuroml/tune/NeuroMLTuner.py
pyneuroml/tune/__init__.py
pyneuroml/utils/__init__.py
pyneuroml/utils/cli.py
pyneuroml/utils/components.py
pyneuroml/utils/info.py
pyneuroml/utils/jnmlwrapper.py
pyneuroml/utils/misc.py
pyneuroml/utils/moose.py
pyneuroml/utils/plot.py
pyneuroml/utils/units.py
pyneuroml-1.3.21.dist-info/licenses/LICENSE.lesser
pyneuroml-1.3.21.dist-info/METADATA
pyneuroml-1.3.21.dist-info/WHEEL
pyneuroml-1.3.21.dist-info/entry_points.txt
pyneuroml-1.3.21.dist-info/top_level.txt
pyneuroml-1.3.21.dist-info/RECORD
