Metadata-Version: 2.4
Name: pyNeuroML
Version: 1.3.21
Summary: Python utilities for NeuroML
Home-page: https://github.com/NeuroML/pyNeuroML
Author: Padraig Gleeson
Author-email: p.gleeson@gmail.com
License: LGPL-3.0-only
Classifier: Intended Audience :: Science/Research
Classifier: License :: OSI Approved :: GNU Lesser General Public License v3 (LGPLv3)
Classifier: Natural Language :: English
Classifier: Operating System :: OS Independent
Classifier: Programming Language :: Python :: 3.9
Classifier: Programming Language :: Python :: 3.10
Classifier: Programming Language :: Python :: 3.11
Classifier: Programming Language :: Python :: 3.12
Classifier: Programming Language :: Python :: 3.13
Classifier: Topic :: Scientific/Engineering
License-File: LICENSE.lesser
Requires-Dist: pylems>=0.6.8
Requires-Dist: airspeed>=0.5.5
Requires-Dist: neuromllite>=0.6.1
Requires-Dist: libNeuroML>=0.6.7
Requires-Dist: matplotlib
Requires-Dist: matplotlib-scalebar
Requires-Dist: progressbar2
Requires-Dist: graphviz
Requires-Dist: typing; python_version < "3.5"
Requires-Dist: lxml
Requires-Dist: numpy
Requires-Dist: sympy
Requires-Dist: ppft[dill]
Provides-Extra: neuron
Requires-Dist: NEURON; extra == "neuron"
Requires-Dist: pyyaml; extra == "neuron"
Provides-Extra: brian
Requires-Dist: Brian2; extra == "brian"
Provides-Extra: netpyne
Requires-Dist: netpyne; extra == "netpyne"
Requires-Dist: NEURON; extra == "netpyne"
Provides-Extra: povray
Requires-Dist: opencv-python; extra == "povray"
Provides-Extra: hdf5
Requires-Dist: tables; extra == "hdf5"
Provides-Extra: analysis
Requires-Dist: pyelectro; extra == "analysis"
Requires-Dist: sympy; extra == "analysis"
Provides-Extra: tune
Requires-Dist: neurotune>=0.2.6; extra == "tune"
Provides-Extra: vispy-common
Requires-Dist: vispy>=0.13.0; extra == "vispy-common"
Requires-Dist: scipy; extra == "vispy-common"
Requires-Dist: pyopengl; extra == "vispy-common"
Requires-Dist: PyOpenGL-accelerate; extra == "vispy-common"
Requires-Dist: scikit-learn; extra == "vispy-common"
Requires-Dist: frozendict; extra == "vispy-common"
Provides-Extra: vispy-qt5
Requires-Dist: pyNeuroML[vispy-common]; extra == "vispy-qt5"
Requires-Dist: pyqt5; extra == "vispy-qt5"
Provides-Extra: vispy
Requires-Dist: pyNeuroML[vispy-common]; extra == "vispy"
Requires-Dist: pyqt6; extra == "vispy"
Provides-Extra: jupyter
Requires-Dist: jupyter; extra == "jupyter"
Requires-Dist: jupyter-rfb; extra == "jupyter"
Requires-Dist: pyNeuroML[vispy-common]; extra == "jupyter"
Provides-Extra: plotly
Requires-Dist: plotly; extra == "plotly"
Provides-Extra: nsg
Requires-Dist: pynsgr; extra == "nsg"
Provides-Extra: annotations
Requires-Dist: rdflib; extra == "annotations"
Provides-Extra: combine
Requires-Dist: python-libsbml; extra == "combine"
Requires-Dist: python-libsedml; extra == "combine"
Requires-Dist: pyNeuroML[annotations]; extra == "combine"
Requires-Dist: pydantic; extra == "combine"
Requires-Dist: requests-toolbelt; extra == "combine"
Provides-Extra: tellurium
Requires-Dist: tellurium; extra == "tellurium"
Provides-Extra: all
Requires-Dist: pyNeuroML[neuron]; extra == "all"
Requires-Dist: pyNeuroML[brian]; extra == "all"
Requires-Dist: pyNeuroML[netpyne]; extra == "all"
Requires-Dist: pyNeuroML[povray]; extra == "all"
Requires-Dist: pyNeuroML[hdf5]; extra == "all"
Requires-Dist: pyNeuroML[analysis]; extra == "all"
Requires-Dist: pyNeuroML[tune]; extra == "all"
Requires-Dist: pyNeuroML[vispy]; extra == "all"
Requires-Dist: pyNeuroML[plotly]; extra == "all"
Requires-Dist: pyNeuroML[nsg]; extra == "all"
Requires-Dist: pyNeuroML[annotations]; extra == "all"
Requires-Dist: pyNeuroML[combine]; extra == "all"
Requires-Dist: pyNeuroML[tellurium]; extra == "all"
Requires-Dist: pyNeuroML[jupyter]; extra == "all"
Provides-Extra: dev
Requires-Dist: pyNeuroML[all]; extra == "dev"
Requires-Dist: pytest; extra == "dev"
Requires-Dist: pytest-cov; extra == "dev"
Requires-Dist: pytest-xdist; extra == "dev"
Requires-Dist: parameterized; extra == "dev"
Requires-Dist: kaleido; extra == "dev"
Requires-Dist: pre-commit; extra == "dev"
Provides-Extra: doc
Requires-Dist: pyNeuroML[all]; extra == "doc"
Requires-Dist: sphinxcontrib-bibtex; extra == "doc"
Requires-Dist: pydata-sphinx-theme; extra == "doc"
Dynamic: license-file
